client_pack/__init__.py
client_pack/client.py
client_pack/client_pack/__init__.py
client_pack/client_pack/add_contact.py
client_pack/client_pack/client_storage.py
client_pack/client_pack/main_window.py
client_pack/client_pack/main_window_conv.py
client_pack/client_pack/remove_contact.py
client_pack/client_pack/start_dialog.py
client_pack/client_pack/transport.py
client_pack/common/__init__.py
client_pack/common/config_path_file.py
client_pack/common/decorators.py
client_pack/common/descriptor.py
client_pack/common/erros.py
client_pack/common/metaclasses.py
client_pack/common/utils.py
client_pack/logs/__init__.py
client_pack/logs/client_log_config.py
client_pack/logs/server_log_config.py
client_pack/unit_tests/__init__.py
client_pack/unit_tests/test_client.py
client_pack/unit_tests/test_server.py
client_pack/unit_tests/test_utils.py
robot_messenger_client-0.1.0.dist-info/METADATA
robot_messenger_client-0.1.0.dist-info/WHEEL
robot_messenger_client-0.1.0.dist-info/top_level.txt
robot_messenger_client-0.1.0.dist-info/RECORD
